{
    "Moderators": {
        "title" : "Обсуждаем претензии, благодарности, недовольство по работе модераторов",
        "description" : "В данной теме вы можете пожаловаться на необоснованный по вашему мнению бан, выданный одним из модераторов сайта. &nbsp; &nbsp;ВНИМАНИЕ! Баны от стримеров и помощников стримеров не рассматриваются!",
        "author" : "Sovremenii",
        "date" : "7 августа в 8:06",
        "dataCall" : 1,
        "dataPost" : 20
    },
    "Moderators1": {
        "title" : "Обсуждаем претензии, благодарности, недовольство по работе модераторов",
        "description" : "В данной теме вы можете пожаловаться на необоснованный по вашему мнению бан, выданный одним из модераторов сайта. &nbsp; &nbsp;ВНИМАНИЕ! Баны от стримеров и помощников стримеров не рассматриваются!",
        "author" : "Sovremenii",
        "date" : "7 августа в 8:06",
        "dataCall" : 1,
        "dataPost" : 20
    }
}